remotecurl/__init__.py
remotecurl/__main__.py
remotecurl/common/__init__.py
remotecurl/common/config.py
remotecurl/common/util.py
remotecurl/modifier/__init__.py
remotecurl/modifier/abstract.py
remotecurl/modifier/css.py
remotecurl/modifier/html.py
remotecurl/modifier/js.py
remotecurl/script/common.js
remotecurl/script/window.js
remotecurl/script/worker.js
remotecurl/server/__init__.py
remotecurl/server/handler.py
remotecurl/server/server.py
remotecurl-1.1.3.dist-info/LICENSE
remotecurl-1.1.3.dist-info/METADATA
remotecurl-1.1.3.dist-info/WHEEL
remotecurl-1.1.3.dist-info/top_level.txt
remotecurl-1.1.3.dist-info/RECORD
