Metadata-Version: 2.1
Name: remotecurl
Version: 1.1.3
Summary: RemoteCurl
Author-email: Wes-KW <dotdotdashdash2024@hotmail.com>
Project-URL: Homepage, https://github.com/Wes-KW/RemoteCurl
Project-URL: Issues, https://github.com/Wes-KW/RemoteCurl/issues
Classifier: Programming Language :: Python :: 3
Classifier: Programming Language :: Python :: 3.5
Classifier: Programming Language :: Python :: 3.6
Classifier: Programming Language :: Python :: 3.7
Classifier: Programming Language :: Python :: 3.8
Classifier: Programming Language :: Python :: 3.9
Classifier: Programming Language :: Python :: 3.10
Classifier: Programming Language :: Python :: 3.11
Classifier: Programming Language :: Python :: 3.12
Classifier: Operating System :: MacOS :: MacOS X
Classifier: Operating System :: Microsoft :: Windows
Classifier: Operating System :: POSIX :: Linux
Requires-Python: <4,>=3.5
License-File: LICENSE
Requires-Dist: beautifulsoup4 >=4.12.3
Requires-Dist: certifi >=2023.11.17
Requires-Dist: jsmin >=3.0.1
Requires-Dist: pycurl >=7.45.3
Requires-Dist: Brotli >=1.1.0
Requires-Dist: zstd >=1.5.5.1
